pelican/__init__.py
pelican/layers.py
pelican/nets.py
pelican/primitives.py
pelican/utils.py
pelican_hep-1.0.3.dist-info/licenses/LICENSE
pelican_hep-1.0.3.dist-info/METADATA
pelican_hep-1.0.3.dist-info/WHEEL
pelican_hep-1.0.3.dist-info/top_level.txt
pelican_hep-1.0.3.dist-info/RECORD
