Metadata-Version: 2.4
Name: pelican-hep
Version: 1.0.3
Summary: Efficient reimplementation of PELICAN (Permutation-Equivariant and Lorentz-Invariant or Covariant Aggregator Network for Particle Physics)
Author-email: Jonas Spinner <j.spinner@thphys.uni-heidelberg.de>
Project-URL: homepage, https://heidelberg-hepml.github.io/pelican
Project-URL: repository, https://github.com/heidelberg-hepml/pelican
Requires-Python: >=3.10
License-File: LICENSE
Requires-Dist: torch>=2.0
Dynamic: license-file
